odoo/addons/purchase_force_invoiced/README.rst
odoo/addons/purchase_force_invoiced/__init__.py
odoo/addons/purchase_force_invoiced/__manifest__.py
odoo/addons/purchase_force_invoiced/i18n/purchase_force_invoiced.pot
odoo/addons/purchase_force_invoiced/i18n/zh_CN.po
odoo/addons/purchase_force_invoiced/model/__init__.py
odoo/addons/purchase_force_invoiced/model/purchase.py
odoo/addons/purchase_force_invoiced/readme/CONTRIBUTORS.rst
odoo/addons/purchase_force_invoiced/readme/DESCRIPTION.rst
odoo/addons/purchase_force_invoiced/readme/USAGE.rst
odoo/addons/purchase_force_invoiced/reports/__init__.py
odoo/addons/purchase_force_invoiced/reports/purchase_report.py
odoo/addons/purchase_force_invoiced/static/description/icon.png
odoo/addons/purchase_force_invoiced/static/description/index.html
odoo/addons/purchase_force_invoiced/tests/__init__.py
odoo/addons/purchase_force_invoiced/tests/test_purchase_force_invoiced.py
odoo/addons/purchase_force_invoiced/view/purchase_view.xml
odoo14_addon_purchase_force_invoiced-14.0.1.0.2.dist-info/METADATA
odoo14_addon_purchase_force_invoiced-14.0.1.0.2.dist-info/WHEEL
odoo14_addon_purchase_force_invoiced-14.0.1.0.2.dist-info/top_level.txt
odoo14_addon_purchase_force_invoiced-14.0.1.0.2.dist-info/RECORD
